templatematchingpy/__init__.py
templatematchingpy/core/__init__.py
templatematchingpy/core/config.py
templatematchingpy/core/stack_alignment.py
templatematchingpy/core/template_matching.py
templatematchingpy/utils/__init__.py
templatematchingpy/utils/image_utils.py
templatematchingpy-1.0.3.dist-info/licenses/LICENSE
templatematchingpy-1.0.3.dist-info/METADATA
templatematchingpy-1.0.3.dist-info/WHEEL
templatematchingpy-1.0.3.dist-info/top_level.txt
templatematchingpy-1.0.3.dist-info/RECORD
