Metadata-Version: 2.4
Name: templatematchingpy
Version: 1.0.3
Summary: Python implementation of ImageJ template matching and stack alignment
Home-page: https://github.com/phisanti/TemplateMatchingPy
Author: TemplateMatchingPy Contributors
Author-email: TemplateMatchingPy Contributors <santiago.canomuniz@unibas.ch>
Maintainer-email: TemplateMatchingPy Contributors <santiago.canomuniz@unibas.ch>
License: EUPL-1.2
Project-URL: Homepage, https://github.com/phisanti/TemplateMatchingPy
Project-URL: Documentation, https://templatematchingpy.readthedocs.io/en/latest/
Project-URL: Repository, https://github.com/phisanti/TemplateMatchingPy
Project-URL: Bug Tracker, https://github.com/phisanti/TemplateMatchingPy/issues
Keywords: image processing,template matching,image alignment,image registration,microscopy,computer vision,opencv,imagej,fiji
Classifier: Development Status :: 5 - Production/Stable
Classifier: Intended Audience :: Science/Research
Classifier: License :: OSI Approved :: European Union Public Licence 1.2 (EUPL 1.2)
Classifier: Operating System :: OS Independent
Classifier: Programming Language :: Python :: 3
Classifier: Programming Language :: Python :: 3.7
Classifier: Programming Language :: Python :: 3.8
Classifier: Programming Language :: Python :: 3.9
Classifier: Programming Language :: Python :: 3.10
Classifier: Programming Language :: Python :: 3.11
Classifier: Topic :: Scientific/Engineering :: Image Processing
Classifier: Topic :: Scientific/Engineering :: Image Recognition
Classifier: Topic :: Software Development :: Libraries :: Python Modules
Requires-Python: >=3.7
License-File: LICENSE
Requires-Dist: numpy>=1.19.0
Requires-Dist: opencv-python>=4.5.0
Provides-Extra: dev
Requires-Dist: pytest>=6.0; extra == "dev"
Requires-Dist: pytest-cov; extra == "dev"
Requires-Dist: black; extra == "dev"
Requires-Dist: flake8; extra == "dev"
Requires-Dist: mypy; extra == "dev"
Provides-Extra: docs
Requires-Dist: sphinx; extra == "docs"
Requires-Dist: sphinx-rtd-theme; extra == "docs"
Requires-Dist: myst-parser; extra == "docs"
Dynamic: author
Dynamic: home-page
Dynamic: license-file
Dynamic: requires-python
